<?xml version="1.0" encoding="UTF-8"?>
<con:testCase id="bcd73f78-b8c5-48b9-8129-3525936086d2" discardOkResults="false" failOnError="true" failTestCaseOnErrors="true" keepSession="false" name="TestCase 1" searchProperties="true" timeout="0" xmlns:con="http://eviware.com/soapui/config">
  <con:settings>
    <con:setting id="bcd73f78-b8c5-48b9-8129-3525936086d2fileName">TestCase-1</con:setting>
  </con:settings>
  <con:savedRecentRuns>1</con:savedRecentRuns>
  <con:testStep type="groovy" name="Groovy Script" id="05b6f74f-be6f-4cee-b9be-0821a0aa60a4">
    <con:settings/>
    <con:config>
      <script/>
    </con:config>
  </con:testStep>
  <con:properties/>
  <con:reportParameters/>
</con:testCase>
